setup.py
Wiki_Bigbluebutton.egg-info/PKG-INFO
Wiki_Bigbluebutton.egg-info/SOURCES.txt
Wiki_Bigbluebutton.egg-info/dependency_links.txt
Wiki_Bigbluebutton.egg-info/requires.txt
Wiki_Bigbluebutton.egg-info/top_level.txt
api/__init__.py
api/admin.py
api/apps.py
api/models.py
api/tests.py
api/views.py
api/migrations/0001_initial.py
api/migrations/__init__.py
package_dash/__init__.py
package_dash/asgi.py
package_dash/settings.py
package_dash/urls.py
package_dash/wsgi.py